fastapi_cprofile/__init__.py
fastapi_cprofile/_version.py
fastapi_cprofile/profiler.py
fastapi_cprofile-0.0.2.dist-info/LICENSE
fastapi_cprofile-0.0.2.dist-info/METADATA
fastapi_cprofile-0.0.2.dist-info/WHEEL
fastapi_cprofile-0.0.2.dist-info/top_level.txt
fastapi_cprofile-0.0.2.dist-info/RECORD
