Metadata-Version: 2.1
Name: fastapi-cprofile
Version: 0.0.2
Summary: A FastAPI Middleware with cProfile to stats your service performance.
Home-page: https://github.com/Jijun/fastapi-cprofile.git
Author: jijunlx
Author-email: jijunlx@gmail.com
License: MIT
Keywords: fastapi,cprofile
Platform: UNKNOWN
Classifier: Development Status :: 5 - Production/Stable
Classifier: Environment :: Console
Classifier: Intended Audience :: Developers
Classifier: License :: OSI Approved :: MIT License
Classifier: Operating System :: OS Independent
Classifier: Programming Language :: Python
Classifier: Programming Language :: Python :: 3.6
Classifier: Programming Language :: Python :: 3.7
Classifier: Programming Language :: Python :: 3.8
Classifier: Programming Language :: Python :: 3.9
Classifier: Topic :: Software Development :: Libraries
Requires-Dist: fastapi
